csvimporteract/__init__.py
csvimporteract/__version__.py
csvimporteract/csvimporter.py
csvimporteract-0.0.26.dist-info/METADATA
csvimporteract-0.0.26.dist-info/WHEEL
csvimporteract-0.0.26.dist-info/top_level.txt
csvimporteract-0.0.26.dist-info/RECORD
