Metadata-Version: 2.1
Name: csvimporteract
Version: 0.0.26
Summary: This helps automating the data preprocess especially for Team ACT
Home-page: https://github.com/SunkyeongLee/csvimporteract
Author: Sunkyeong Lee
Author-email: sunkyeong.lee@concentrix.com
Classifier: Programming Language :: Python :: 3
Classifier: License :: OSI Approved :: MIT License
Classifier: Operating System :: OS Independent
Requires-Python: >=3.6
